industream/__init__.py
industream/flowmaker/__init__.py
industream/flowmaker/sdk/__init__.py
industream/flowmaker/sdk/flowbox.py
industream/flowmaker/sdk/flowbox_core.py
industream/flowmaker/sdk/flowbox_decorator.py
industream/flowmaker/sdk/flowbox_init_params.py
industream/flowmaker/sdk/flowbox_registration_info.py
industream/flowmaker/sdk/flowmaker_event.py
industream/flowmaker/sdk/flowmaker_worker.py
industream/flowmaker/sdk/flowmaker_worker_builder.py
industream/flowmaker/sdk/flowmaker_worker_options.py
industream/flowmaker/sdk/py.typed
industream_flowmaker_sdk-1.0.3.dist-info/METADATA
industream_flowmaker_sdk-1.0.3.dist-info/WHEEL
industream_flowmaker_sdk-1.0.3.dist-info/RECORD
